azure_functions/perper/__init__.py
azure_functions/perper/_perper.py
azure_functions/perper/perper.py
azure_functions_perper_binding-0.5.1.dist-info/METADATA
azure_functions_perper_binding-0.5.1.dist-info/WHEEL
azure_functions_perper_binding-0.5.1.dist-info/top_level.txt
azure_functions_perper_binding-0.5.1.dist-info/RECORD
