Metadata-Version: 2.1
Name: azure-functions-perper-binding
Version: 0.5.1
Summary: UNKNOWN
Home-page: https://github.com/obecto/perper
Author: Obecto EOOD
License: MIT License
Platform: UNKNOWN
Classifier: Development Status :: 3 - Alpha
Classifier: Programming Language :: Python :: 3.6
Classifier: Operating System :: OS Independent
Classifier: License :: OSI Approved :: MIT License
Requires-Dist: azure-functions-worker
Requires-Dist: pyignite
